infrared/__init__.py
infrared/api.py
infrared/bash_completers.py
infrared/main.py
infrared/common/README.md
infrared/common/callback_plugins/README.rst
infrared/common/filter_plugins/README.rst
infrared/common/filter_plugins/absolute_path.py
infrared/common/filter_plugins/from_csv.py
infrared/common/filter_plugins/from_xml.py
infrared/common/filter_plugins/openstack_release.py
infrared/common/library/redhat_subscription.py
infrared/common/library/rhos_release.py
infrared/common/library/virt_util.py
infrared/common/roles/README.rst
infrared/common/roles/cdn_registery/defaults/main.yml
infrared/common/roles/cdn_registery/tasks/main.yml
infrared/common/roles/cdn_registery/tasks/register_cdn.yml
infrared/common/roles/collect-ansible-facts/defaults/main.yml
infrared/common/roles/collect-ansible-facts/tasks/main.yml
infrared/common/roles/inventory-update/README.rst
infrared/common/roles/inventory-update/defaults/main.yml
infrared/common/roles/inventory-update/tasks/main.yml
infrared/common/roles/inventory-update/templates/inventory.j2
infrared/common/roles/rdo-release/defaults/main.yml
infrared/common/roles/rdo-release/tasks/main.yml
infrared/common/roles/rdo-release/tasks/public-repos.yml
infrared/common/roles/rdo-release/tasks/rdo-release.yml
infrared/common/roles/rhos-release/defaults/main.yml
infrared/common/roles/rhos-release/files/select-mirror.sh
infrared/common/roles/rhos-release/files/use-mirror.sh
infrared/common/roles/rhos-release/tasks/main.yml
infrared/common/roles/shade/README.rst
infrared/common/roles/shade/defaults/main.yml
infrared/common/roles/shade/tasks/main.yml
infrared/common/roles/tls-everywhere/README.rst
infrared/common/roles/tls-everywhere/defaults/main.yml
infrared/common/roles/tls-everywhere/tasks/main.yml
infrared/common/roles/tls-everywhere/tasks/post_overcloud.yml
infrared/common/roles/tls-everywhere/tasks/prepare_freeipa.yml
infrared/common/roles/tls-everywhere/tasks/prepare_overcloud.yml
infrared-3.0.2.dist-info/DESCRIPTION.rst
infrared-3.0.2.dist-info/METADATA
infrared-3.0.2.dist-info/RECORD
infrared-3.0.2.dist-info/WHEEL
infrared-3.0.2.dist-info/entry_points.txt
infrared-3.0.2.dist-info/metadata.json
infrared-3.0.2.dist-info/pbr.json
infrared-3.0.2.dist-info/top_level.txt
